klovis/.env
klovis/.env.example
klovis/.git/COMMIT_EDITMSG
klovis/.git/HEAD
klovis/.git/config
klovis/.git/description
klovis/.git/hooks/applypatch-msg.sample
klovis/.git/hooks/commit-msg.sample
klovis/.git/hooks/fsmonitor-watchman.sample
klovis/.git/hooks/post-update.sample
klovis/.git/hooks/pre-applypatch.sample
klovis/.git/hooks/pre-commit.sample
klovis/.git/hooks/pre-merge-commit.sample
klovis/.git/hooks/pre-push.sample
klovis/.git/hooks/pre-rebase.sample
klovis/.git/hooks/pre-receive.sample
klovis/.git/hooks/prepare-commit-msg.sample
klovis/.git/hooks/push-to-checkout.sample
klovis/.git/hooks/update.sample
klovis/.git/index
klovis/.git/info/exclude
klovis/.git/logs/HEAD
klovis/.git/logs/refs/heads/main
klovis/.git/logs/refs/remotes/origin/main
klovis/.git/objects/00/9a011de6a788fb6100551ae882fcd4fb540a7f
klovis/.git/objects/01/18171c6258d284547d5e4cbec8b1929ee158ce
klovis/.git/objects/01/5ae86821d5e087d781fbe7ca9a736a7ae58544
klovis/.git/objects/01/790a2b23835897925209436413974a71f26387
klovis/.git/objects/02/6604a1230ffb9434b47eb753c96a8e25e12d3c
klovis/.git/objects/03/c50fa931f7fa85f4241f61f22a899a50e1b786
klovis/.git/objects/07/36b0e96cde86bf74a69b58d3bdf3dab4e8d828
klovis/.git/objects/07/cf4ad135c309f167bd3da2544e38ce88833a69
klovis/.git/objects/0d/81146dc55c5f9a7652f8df9507c03f75029977
klovis/.git/objects/0e/f2e2fd165c0953c53d94a0fbe5ffabca2df22e
klovis/.git/objects/0f/0aa3d380ef6b05af8b917742ef0b43c783bc3a
klovis/.git/objects/0f/120052a01a36520d2e7ae9b58c742ecebca5aa
klovis/.git/objects/0f/d4450b89c04ca1fcf1a41def3576ce642ca2e8
klovis/.git/objects/10/24e593daea160a1bc579423c7b23c9e6a951a8
klovis/.git/objects/10/f86c2a6700313bd07277892d46d158acaa7ecb
klovis/.git/objects/11/6dea65895f87a707b92156963ee075996375a2
klovis/.git/objects/11/9ee41054eed89d5ce799b8faa638adbba588b6
klovis/.git/objects/12/7647ea4116134fb73d9005143824c288854c09
klovis/.git/objects/13/f43e245d1fff4f93e4fd1d69c13596032720a5
klovis/.git/objects/14/0a5e0c6728da5d943d9a5dd246c4f3448f4c1e
klovis-0.6.1.dist-info/METADATA
klovis-0.6.1.dist-info/WHEEL
klovis-0.6.1.dist-info/licenses/LICENSE
klovis-0.6.1.dist-info/RECORD
