Metadata-Version: 2.4
Name: klovis
Version: 0.6.1
Summary: Data preprocessing library for Retrieval-Augmented Generation (RAG) systems.
License: LICENSE
License-File: LICENSE
Keywords: RAG,data preprocessing,AI,semantic,embedding
Author: Houzelle Eric
Author-email: eric@klovis.ai
Requires-Python: >=3.10,<4.0
Classifier: License :: Other/Proprietary License
Classifier: Programming Language :: Python :: 3
Classifier: Programming Language :: Python :: 3.10
Classifier: Programming Language :: Python :: 3.11
Classifier: Programming Language :: Python :: 3.12
Classifier: Programming Language :: Python :: 3.13
Classifier: Programming Language :: Python :: 3.14
Provides-Extra: embeddings
Provides-Extra: embeddings-cpu
Requires-Dist: beautifulsoup4 (>=4.14.2,<5.0.0)
Requires-Dist: markdown-it-py (>=3.0.0,<4.0.0)
Requires-Dist: markdownify (>=1.2.0,<2.0.0)
Requires-Dist: numpy (>=2.0.0)
Requires-Dist: openai (>=2.8.0,<3.0.0)
Requires-Dist: pandas (>=2.2.0,<3.0.0)
Requires-Dist: pdfplumber (>=0.11.8,<0.12.0)
Requires-Dist: pyarrow (>=12.0.0)
Requires-Dist: pydantic (>=2.9.0,<3.0.0)
Requires-Dist: python-dotenv (>=1.0.1,<2.0.0)
Requires-Dist: requests (>=2.32.0,<3.0.0)
Requires-Dist: scikit-learn (>=1.7.2,<2.0.0)
Requires-Dist: sentence-transformers (>=5.1.2,<6.0.0) ; extra == "embeddings" or extra == "embeddings-cpu"
Requires-Dist: spacy (>=3.7,<4.0)
Requires-Dist: torch (==2.5.1+cpu) ; extra == "embeddings-cpu"
Project-URL: Homepage, https://github.com/klovis-ai/klovis
Project-URL: Repository, https://github.com/klovis-ai/klovis
